ensureTaskCanceled/__init__.py
ensureTaskCanceled/ensureTaskCanceled.py
ensureTaskCanceled-1.1.dist-info/LICENSE
ensureTaskCanceled-1.1.dist-info/METADATA
ensureTaskCanceled-1.1.dist-info/WHEEL
ensureTaskCanceled-1.1.dist-info/top_level.txt
ensureTaskCanceled-1.1.dist-info/RECORD
