Metadata-Version: 2.1
Name: ensureTaskCanceled
Version: 1.1
Summary: Keep cancelling a asyncio.Task instance, until it is done.
Home-page: https://github.com/monk-after-90s/ensureTaskCanceled.git
Author: Antas
Author-email: 
License: UNKNOWN
Platform: UNKNOWN
Classifier: Programming Language :: Python :: 3
Classifier: License :: OSI Approved :: MIT License
Classifier: Operating System :: OS Independent
Requires-Python: >=3.6
